{"nodes": [{"id": "docker_redis", "label": "Docker Redis Service", "file_type": "document", "source_file": "docker-compose.yml", "source_location": null}, {"id": "docker_leadminer_api", "label": "Docker Leadminer API", "file_type": "document", "source_file": "docker-compose.yml", "source_location": null}, {"id": "docker_email_fetcher", "label": "Docker Email Fetcher Service", "file_type": "document", "source_file": "docker-compose.yml", "source_location": null}, {"id": "docker_contact_worker", "label": "Docker Contact Extraction Worker", "file_type": "document", "source_file": "docker-compose.yml", "source_location": null}, {"id": "docker_email_verification_worker", "label": "Docker Email Verification Worker", "file_type": "document", "source_file": "docker-compose.yml", "source_location": null}, {"id": "docker_signature_worker", "label": "Docker Signature Worker", "file_type": "document", "source_file": "docker-compose.yml", "source_location": null}, {"id": "docker_frontend", "label": "Docker Frontend Service", "file_type": "document", "source_file": "docker-compose.yml", "source_location": null}], "edges": [{"source": "docker_leadminer_api", "target": "docker_redis", "relation": "references", "confidence": "EXTRACTED", "confidence_score": 1.0, "source_file": "docker-compose.yml", "weight": 1.0}, {"source": "docker_email_fetcher", "target": "docker_redis", "relation": "references", "confidence": "EXTRACTED", "confidence_score": 1.0, "source_file": "docker-compose.yml", "weight": 1.0}, {"source": "docker_contact_worker", "target": "docker_redis", "relation": "references", "confidence": "EXTRACTED", "confidence_score": 1.0, "source_file": "docker-compose.yml", "weight": 1.0}, {"source": "docker_email_verification_worker", "target": "docker_redis", "relation": "references", "confidence": "EXTRACTED", "confidence_score": 1.0, "source_file": "docker-compose.yml", "weight": 1.0}, {"source": "docker_signature_worker", "target": "docker_redis", "relation": "references", "confidence": "EXTRACTED", "confidence_score": 1.0, "source_file": "docker-compose.yml", "weight": 1.0}, {"source": "docker_frontend", "target": "docker_leadminer_api", "relation": "references", "confidence": "EXTRACTED", "confidence_score": 1.0, "source_file": "docker-compose.yml", "weight": 1.0}, {"source": "docker_contact_worker", "target": "docker_email_verification_worker", "relation": "semantically_similar_to", "confidence": "INFERRED", "confidence_score": 0.8, "source_file": "docker-compose.yml", "weight": 1.0}, {"source": "docker_contact_worker", "target": "docker_signature_worker", "relation": "semantically_similar_to", "confidence": "INFERRED", "confidence_score": 0.8, "source_file": "docker-compose.yml", "weight": 1.0}, {"source": "docker_email_verification_worker", "target": "docker_signature_worker", "relation": "semantically_similar_to", "confidence": "INFERRED", "confidence_score": 0.8, "source_file": "docker-compose.yml", "weight": 1.0}], "hyperedges": [{"id": "docker_worker_services", "label": "Background Worker Services", "nodes": ["docker_contact_worker", "docker_email_verification_worker", "docker_signature_worker"], "relation": "participate_in", "confidence": "EXTRACTED", "confidence_score": 0.95, "source_file": "docker-compose.yml"}]}